{
    "adult": false,
    "backdrop_path": "/fev8UFNFFYsD5q7AcYS8LyTzqwl.jpg",
    "genre_ids": [
        28,
        35,
        10751
    ],
    "id": 587807,
    "original_language": "en",
    "original_title": "Tom & Jerry",
    "overview": "Tom the cat and Jerry the mouse get kicked out of their home and relocate to a fancy New York hotel, where a scrappy employee named Kayla will lose her job if she can’t evict Jerry before a high-class wedding at the hotel. Her solution? Hiring Tom to get rid of the pesky mouse.",
    "popularity": 2187.959,
    "poster_path": "/6KErczPBROQty7QoIsaa6wJYXZi.jpg",
    "release_date": "2021-02-11",
    "title": "Tom & Jerry",
    "video": false,
    "vote_average": 7.4,
    "vote_count": 980,
    "belongs_to_collection": null,
    "budget": 50000000,
    "genres": [
        {
            "id": 28,
            "name": "Action"
        },
        {
            "id": 35,
            "name": "Comedy"
        },
        {
            "id": 10751,
            "name": "Family"
        }
    ],
    "homepage": "https://www.tomandjerrymovie.com",
    "imdb_id": "tt1361336",
    "production_companies": [
        {
            "id": 25120,
            "logo_path": "/lqUpBvDLQYG3QaKNpe2lxfpgh36.png",
            "name": "Warner Animation Group",
            "origin_country": "US"
        },
        {
            "id": 174,
            "logo_path": "/ky0xOc5OrhzkZ1N6KyUxacfQsCk.png",
            "name": "Warner Bros. Pictures",
            "origin_country": "US"
        },
        {
            "id": 8922,
            "logo_path": "/yZWehAyjfKi4KvKeg1bkJ1bm5H8.png",
            "name": "Turner Entertainment",
            "origin_country": "US"
        },
        {
            "id": 77061,
            "logo_path": null,
            "name": "The Story Company",
            "origin_country": ""
        }
    ],
    "production_countries": [
        {
            "iso_3166_1": "US",
            "name": "United States of America"
        }
    ],
    "revenue": 66890000,
    "runtime": 101,
    "spoken_languages": [
        {
            "english_name": "English",
            "iso_639_1": "en",
            "name": "English"
        }
    ],
    "status": "Released",
    "tagline": "Best of enemies. Worst of friends.",
    "trakt": {
        "base": {
            "title": "Tom & Jerry",
            "year": 2021,
            "ids": {
                "trakt": 435024,
                "slug": "tom-jerry-2021",
                "imdb": "tt1361336",
                "tmdb": 587807
            }
        },
        "aliases": [
            {
                "title": "Tom and Jerry",
                "country": "us"
            },
            {
                "title": "Tom and Jerry: Chase",
                "country": "es"
            },
            {
                "title": "湯姆貓與傑利鼠",
                "country": "tw"
            },
            {
                "title": "Tom och Jerry",
                "country": "se"
            },
            {
                "title": "Tom and Jerry 2021",
                "country": "tz"
            },
            {
                "title": "Tom & Jerry The Movie",
                "country": "au"
            },
            {
                "title": "猫和老鼠",
                "country": "cn"
            },
            {
                "title": "Tom & Jerry: The Movie",
                "country": "gb"
            },
            {
                "title": "Tom & Jerry: A Major Commotion Picture",
                "country": "us"
            },
            {
                "title": "Tom & Jerry",
                "country": "br"
            }
        ],
        "releases": [
            {
                "country": "br",
                "certification": "L",
                "release_date": "2021-02-11",
                "release_type": "theatrical",
                "note": null
            },
            {
                "country": "co",
                "certification": "",
                "release_date": "2021-02-12",
                "release_type": "theatrical",
                "note": null
            },
            {
                "country": "kr",
                "certification": "ALL",
                "release_date": "2021-02-24",
                "release_type": "theatrical",
                "note": null
            },
            {
                "country": "ru",
                "certification": "6+",
                "release_date": "2021-02-25",
                "release_type": "theatrical",
                "note": null
            },
            {
                "country": "us",
                "certification": "PG",
                "release_date": "2021-02-26",
                "release_type": "digital",
                "note": "HBO Max"
            },
            {
                "country": "us",
                "certification": "PG",
                "release_date": "2021-02-26",
                "release_type": "digital",
                "note": "HBO Max"
            },
            {
                "country": "us",
                "certification": "PG",
                "release_date": "2021-02-26",
                "release_type": "digital",
                "note": "HBO Max"
            },
            {
                "country": "us",
                "certification": "PG",
                "release_date": "2021-02-26",
                "release_type": "digital",
                "note": "HBO Max"
            },
            {
                "country": "us",
                "certification": "PG",
                "release_date": "2021-02-26",
                "release_type": "digital",
                "note": "HBO Max"
            },
            {
                "country": "us",
                "certification": "PG",
                "release_date": "2021-02-26",
                "release_type": "digital",
                "note": "HBO Max"
            },
            {
                "country": "us",
                "certification": "PG",
                "release_date": "2021-02-26",
                "release_type": "digital",
                "note": "HBO Max"
            },
            {
                "country": "us",
                "certification": "PG",
                "release_date": "2021-02-26",
                "release_type": "digital",
                "note": "HBO Max"
            },
            {
                "country": "us",
                "certification": "PG",
                "release_date": "2021-02-26",
                "release_type": "digital",
                "note": "HBO Max"
            },
            {
                "country": "us",
                "certification": "PG",
                "release_date": "2021-02-26",
                "release_type": "digital",
                "note": "HBO Max"
            },
            {
                "country": "us",
                "certification": "PG",
                "release_date": "2021-02-26",
                "release_type": "digital",
                "note": "HBO Max"
            },
            {
                "country": "us",
                "certification": "PG",
                "release_date": "2021-02-26",
                "release_type": "digital",
                "note": "HBO Max"
            },
            {
                "country": "us",
                "certification": "PG",
                "release_date": "2021-02-26",
                "release_type": "digital",
                "note": "HBO Max"
            },
            {
                "country": "us",
                "certification": "PG",
                "release_date": "2021-02-26",
                "release_type": "digital",
                "note": "HBO Max"
            },
            {
                "country": "us",
                "certification": "PG",
                "release_date": "2021-02-26",
                "release_type": "digital",
                "note": "HBO Max"
            },
            {
                "country": "us",
                "certification": "PG",
                "release_date": "2021-02-26",
                "release_type": "theatrical",
                "note": null
            },
            {
                "country": "us",
                "certification": "PG",
                "release_date": "2021-02-26",
                "release_type": "digital",
                "note": "HBO Max"
            },
            {
                "country": "us",
                "certification": "PG",
                "release_date": "2021-02-26",
                "release_type": "digital",
                "note": "HBO Max"
            },
            {
                "country": "us",
                "certification": "PG",
                "release_date": "2021-02-26",
                "release_type": "digital",
                "note": "HBO Max"
            },
            {
                "country": "us",
                "certification": "PG",
                "release_date": "2021-02-26",
                "release_type": "digital",
                "note": "HBO Max"
            },
            {
                "country": "us",
                "certification": "PG",
                "release_date": "2021-02-26",
                "release_type": "digital",
                "note": "HBO Max"
            },
            {
                "country": "us",
                "certification": "PG",
                "release_date": "2021-02-26",
                "release_type": "digital",
                "note": "HBO Max"
            },
            {
                "country": "us",
                "certification": "PG",
                "release_date": "2021-02-26",
                "release_type": "digital",
                "note": "HBO Max"
            },
            {
                "country": "us",
                "certification": "PG",
                "release_date": "2021-02-26",
                "release_type": "digital",
                "note": "HBO Max"
            },
            {
                "country": "us",
                "certification": "PG",
                "release_date": "2021-02-26",
                "release_type": "digital",
                "note": "HBO Max"
            },
            {
                "country": "us",
                "certification": "PG",
                "release_date": "2021-02-26",
                "release_type": "digital",
                "note": "HBO Max"
            },
            {
                "country": "us",
                "certification": "PG",
                "release_date": "2021-02-26",
                "release_type": "digital",
                "note": "HBO Max"
            },
            {
                "country": "us",
                "certification": "PG",
                "release_date": "2021-02-26",
                "release_type": "digital",
                "note": "HBO Max"
            },
            {
                "country": "us",
                "certification": "PG",
                "release_date": "2021-02-26",
                "release_type": "digital",
                "note": "HBO Max"
            },
            {
                "country": "us",
                "certification": "PG",
                "release_date": "2021-02-26",
                "release_type": "digital",
                "note": "HBO Max"
            },
            {
                "country": "us",
                "certification": "PG",
                "release_date": "2021-02-26",
                "release_type": "digital",
                "note": "HBO Max"
            },
            {
                "country": "us",
                "certification": "PG",
                "release_date": "2021-02-26",
                "release_type": "digital",
                "note": "HBO Max"
            },
            {
                "country": "us",
                "certification": "PG",
                "release_date": "2021-02-26",
                "release_type": "digital",
                "note": "HBO Max"
            },
            {
                "country": "us",
                "certification": "PG",
                "release_date": "2021-02-26",
                "release_type": "digital",
                "note": "HBO Max"
            },
            {
                "country": "us",
                "certification": "PG",
                "release_date": "2021-02-26",
                "release_type": "digital",
                "note": "HBO Max"
            },
            {
                "country": "us",
                "certification": "PG",
                "release_date": "2021-02-26",
                "release_type": "digital",
                "note": "HBO Max"
            },
            {
                "country": "us",
                "certification": "PG",
                "release_date": "2021-02-26",
                "release_type": "digital",
                "note": "HBO Max"
            },
            {
                "country": "us",
                "certification": "PG",
                "release_date": "2021-02-26",
                "release_type": "digital",
                "note": "HBO Max"
            },
            {
                "country": "us",
                "certification": "PG",
                "release_date": "2021-02-26",
                "release_type": "digital",
                "note": "HBO Max"
            },
            {
                "country": "us",
                "certification": "PG",
                "release_date": "2021-02-26",
                "release_type": "digital",
                "note": "HBO Max"
            },
            {
                "country": "us",
                "certification": "PG",
                "release_date": "2021-02-26",
                "release_type": "theatrical",
                "note": null
            },
            {
                "country": "us",
                "certification": "PG",
                "release_date": "2021-02-26",
                "release_type": "theatrical",
                "note": null
            },
            {
                "country": "us",
                "certification": "PG",
                "release_date": "2021-02-26",
                "release_type": "theatrical",
                "note": null
            },
            {
                "country": "us",
                "certification": "PG",
                "release_date": "2021-02-26",
                "release_type": "theatrical",
                "note": null
            },
            {
                "country": "us",
                "certification": "PG",
                "release_date": "2021-02-26",
                "release_type": "theatrical",
                "note": null
            },
            {
                "country": "us",
                "certification": "PG",
                "release_date": "2021-02-26",
                "release_type": "theatrical",
                "note": null
            },
            {
                "country": "us",
                "certification": "PG",
                "release_date": "2021-02-26",
                "release_type": "theatrical",
                "note": null
            },
            {
                "country": "us",
                "certification": "PG",
                "release_date": "2021-02-26",
                "release_type": "theatrical",
                "note": null
            },
            {
                "country": "us",
                "certification": "PG",
                "release_date": "2021-02-26",
                "release_type": "theatrical",
                "note": null
            },
            {
                "country": "us",
                "certification": "PG",
                "release_date": "2021-02-26",
                "release_type": "digital",
                "note": "HBO Max"
            },
            {
                "country": "us",
                "certification": "PG",
                "release_date": "2021-02-26",
                "release_type": "digital",
                "note": "HBO Max"
            },
            {
                "country": "us",
                "certification": "PG",
                "release_date": "2021-02-26",
                "release_type": "theatrical",
                "note": null
            },
            {
                "country": "us",
                "certification": "PG",
                "release_date": "2021-02-26",
                "release_type": "digital",
                "note": "HBO Max"
            },
            {
                "country": "us",
                "certification": "PG",
                "release_date": "2021-02-26",
                "release_type": "digital",
                "note": "HBO Max"
            },
            {
                "country": "us",
                "certification": "PG",
                "release_date": "2021-02-26",
                "release_type": "digital",
                "note": "HBO Max"
            },
            {
                "country": "us",
                "certification": "PG",
                "release_date": "2021-02-26",
                "release_type": "digital",
                "note": "HBO Max"
            },
            {
                "country": "us",
                "certification": "PG",
                "release_date": "2021-02-26",
                "release_type": "digital",
                "note": "HBO Max"
            },
            {
                "country": "us",
                "certification": "PG",
                "release_date": "2021-02-26",
                "release_type": "theatrical",
                "note": null
            },
            {
                "country": "us",
                "certification": "PG",
                "release_date": "2021-02-26",
                "release_type": "digital",
                "note": "HBO Max"
            },
            {
                "country": "us",
                "certification": "PG",
                "release_date": "2021-02-26",
                "release_type": "digital",
                "note": "HBO Max"
            },
            {
                "country": "us",
                "certification": "PG",
                "release_date": "2021-02-26",
                "release_type": "digital",
                "note": "HBO Max"
            },
            {
                "country": "us",
                "certification": "PG",
                "release_date": "2021-02-26",
                "release_type": "theatrical",
                "note": null
            },
            {
                "country": "us",
                "certification": "PG",
                "release_date": "2021-02-26",
                "release_type": "theatrical",
                "note": null
            },
            {
                "country": "us",
                "certification": "PG",
                "release_date": "2021-02-26",
                "release_type": "digital",
                "note": "HBO Max"
            },
            {
                "country": "us",
                "certification": "PG",
                "release_date": "2021-02-26",
                "release_type": "digital",
                "note": "HBO Max"
            },
            {
                "country": "us",
                "certification": "PG",
                "release_date": "2021-02-26",
                "release_type": "digital",
                "note": "HBO Max"
            },
            {
                "country": "us",
                "certification": "PG",
                "release_date": "2021-02-26",
                "release_type": "digital",
                "note": "HBO Max"
            },
            {
                "country": "us",
                "certification": "PG",
                "release_date": "2021-02-26",
                "release_type": "digital",
                "note": "HBO Max"
            },
            {
                "country": "us",
                "certification": "PG",
                "release_date": "2021-02-26",
                "release_type": "digital",
                "note": "HBO Max"
            },
            {
                "country": "us",
                "certification": "PG",
                "release_date": "2021-02-26",
                "release_type": "theatrical",
                "note": null
            },
            {
                "country": "us",
                "certification": "PG",
                "release_date": "2021-02-26",
                "release_type": "digital",
                "note": "HBO Max"
            },
            {
                "country": "us",
                "certification": "PG",
                "release_date": "2021-02-26",
                "release_type": "digital",
                "note": "HBO Max"
            },
            {
                "country": "us",
                "certification": "PG",
                "release_date": "2021-02-26",
                "release_type": "digital",
                "note": "HBO Max"
            },
            {
                "country": "us",
                "certification": "PG",
                "release_date": "2021-02-26",
                "release_type": "digital",
                "note": "HBO Max"
            },
            {
                "country": "us",
                "certification": "PG",
                "release_date": "2021-02-26",
                "release_type": "digital",
                "note": "HBO Max"
            },
            {
                "country": "us",
                "certification": "PG",
                "release_date": "2021-02-26",
                "release_type": "digital",
                "note": "HBO Max"
            },
            {
                "country": "us",
                "certification": "PG",
                "release_date": "2021-02-26",
                "release_type": "digital",
                "note": "HBO Max"
            },
            {
                "country": "us",
                "certification": "PG",
                "release_date": "2021-02-26",
                "release_type": "theatrical",
                "note": null
            },
            {
                "country": "us",
                "certification": "PG",
                "release_date": "2021-02-26",
                "release_type": "theatrical",
                "note": null
            },
            {
                "country": "us",
                "certification": "PG",
                "release_date": "2021-02-26",
                "release_type": "theatrical",
                "note": null
            },
            {
                "country": "us",
                "certification": "PG",
                "release_date": "2021-02-26",
                "release_type": "digital",
                "note": "HBO Max"
            },
            {
                "country": "pt",
                "certification": "M/6",
                "release_date": "2021-03-04",
                "release_type": "theatrical",
                "note": null
            },
            {
                "country": "id",
                "certification": "",
                "release_date": "2021-03-10",
                "release_type": "theatrical",
                "note": null
            },
            {
                "country": "gb",
                "certification": "PG",
                "release_date": "2021-03-25",
                "release_type": "digital",
                "note": null
            },
            {
                "country": "nl",
                "certification": "6",
                "release_date": "2021-04-21",
                "release_type": "theatrical",
                "note": null
            },
            {
                "country": "ie",
                "certification": "G",
                "release_date": "2021-05-07",
                "release_type": "theatrical",
                "note": null
            }
        ],
        "translations": [
            {
                "title": "القط جيري و الفأر توم",
                "overview": "يُطرد توم القط والفأر جيري من منزلهما وينتقلان إلى فندق فخم في نيويورك ، حيث ستفقد موظفة فظة تدعى كايلا وظيفتها إذا لم تستطع طرد جيري قبل حفل زفاف رفيع المستوى في الفندق. حلها؟ توظيف توم للتخلص من الفأر المزعج.",
                "tagline": "أفضل الأعداء. أسوأ الأصدقاء.",
                "language": "ar"
            },
            {
                "title": "Том и Джери",
                "overview": "",
                "tagline": "",
                "language": "bg"
            },
            {
                "title": "Tom & Jerry",
                "overview": "Když se Jerry přestěhuje do luxusního hotelu na Manhattanu, kde právě probíhá svatba století, její zoufalá organizátorka si najme Toma, aby jí pomohl se myšáka zbavit. Hon kocoura a myši vzápětí skoro zničí nejen její kariéru a chystanou svatbu, ale i skoro celý hotel.",
                "tagline": "Nejlepší nepřátelé. Nejhorší  přátelé.",
                "language": "cs"
            },
            {
                "title": "Tom & Jerry",
                "overview": "Nogle af historiens mest elskede fjender genoptager deres fejde, da Jerry flytter ind på New York City's fineste hotel dagen inden århundredets bryllup. Det tvinger den desperate bryllupsarrangør til at hyre Tom, så katten kan fjerne den uønskede mus. Den følgende kamp mellem katten og musen truer med at ødelægge bryllupsarrangørens karriere, brylluppet - og måske endda også hotellet. Men snart opstår der et endnu større problem: en djævelsk, ambitiøs medarbejder, der konspirerer mod dem alle tre.",
                "tagline": "Bedste fjender. Værste venner.",
                "language": "da"
            },
            {
                "title": "Tom & Jerry",
                "overview": "Als es sich die kleine Maus Jerry in einem New Yorker Nobelhotel bequem macht, wird die junge Angestellte Kayla (Chloë Grace Moretz) damit betraut, den Nager wieder loszuwerden. Dafür schleppt sie schließlich den Straßenkater Tom an, der schnell Jagd auf Jerry macht, dabei aber nur für noch mehr Chaos im Hotel sorgt. Da Kaylas hinterhältiger Vorgesetzter Terrance (Michael Peña) ihr bald immer mehr Steine in den Weg legt und auch Toms und Jerrys Leben mehr und mehr zur Hölle macht, sehen sich die tierischen Rivalen und Kayla schließlich dazu gezwungen, sich zusammenzuraufen, um Terrance‘ Treiben mit vereinten Kräften ein Ende zu bereiten.",
                "tagline": "",
                "language": "de"
            },
            {
                "title": "Τομ & Τζέρυ",
                "overview": "Ο Τομ η γάτα και ο Τζέρι το ποντίκι βγαίνουν έξω από το σπίτι τους και μεταφέρονται σε ένα φανταχτερό ξενοδοχείο της Νέας Υόρκης, όπου ένας άκαμπτος υπάλληλος που ονομάζεται Kayla θα χάσει τη δουλειά του εάν δεν μπορεί να εκδιώξει τον Τζέρι πριν από έναν γάμο υψηλού επιπέδου στο ξενοδοχείο. Η λύση της; Πρόσληψη του Tom για να απαλλαγούμε από το ενοχλητικό ποντίκι .",
                "tagline": "",
                "language": "el"
            },
            {
                "title": "Tom & Jerry",
                "overview": "Tom the cat and Jerry the mouse get kicked out of their home and relocate to a fancy New York hotel, where a scrappy employee named Kayla will lose her job if she can’t evict Jerry before a high-class wedding at the hotel. Her solution? Hiring Tom to get rid of the pesky mouse.",
                "tagline": "Best of enemies. Worst of friends.",
                "language": "en"
            },
            {
                "title": "Tom y Jerry",
                "overview": "Tom el gato y Jerry el ratón son expulsados de su casa y se trasladan a un elegante hotel de Nueva York, donde una empleada descuidada llamada Kayla perderá su trabajo si no puede desalojar a Jerry antes de una boda de clase alta en el hotel. ¿Su solución? Contratar a Tom para deshacerse del molesto ratón.",
                "tagline": "Los mejores enemigos. Los peores amigos.",
                "language": "es"
            },
            {
                "title": "Tom & Jerry",
                "overview": "Kun Jerry muuttaa New Yorkin hienoimpaan hotelliin juuri ennen siellä järjestettäviä ”vuosisadan häitä”, epätoivoinen hääsuunnittelija joutuu palkkamaan Tomin päästäkseen eroon hiirestä. Hurja kissa ja hiiri -taistelu uhkaa tuhota hääsuunnittelijan uran, itse häätilaisuuden sekä mahdollisesti koko hotellin. Mutta pian ilmenee suurempi ongelma, sillä pahantahtoinen hotellin työntekijä alkaakin juonitella kaikkia kolmea vastaan.",
                "tagline": "Parhaimmat viholliset. Pahimmat ystävät.",
                "language": "fi"
            },
            {
                "title": "Tom & Jerry",
                "overview": "Tom, le chat et Jerry, la souris n'ont plus de domicile. Ils emménagent dans un hôtel chic de New York où Kayla a trouvé un emploi. Mais pour qu'elle puisse le garder, il faut impérativement qu'elle chasse Jerry avant la réception d'un mariage...",
                "tagline": "Même les meilleurs amis se chat-maillent",
                "language": "fr"
            },
            {
                "title": "טום וג'רי",
                "overview": "היריבות האגדית מתעוררת מחדש כשג'רי עובר למלון המשובח ביותר בעיר ניו ורק ערב חתונת המאה, ומכריח את מתכננת האירועים הנואשת להעסיק את טום כדי להיפטר ממנו. ככל שמתגברת המהומה, הקרב החתול והעכבר המתגבר מאיים להרוס את הקריירה שלה, את החתונה ואולי את המלון עצמו.",
                "tagline": "האויבים הכי טובים והחברים הכי גרועים.",
                "language": "he"
            },
            {
                "title": "Tom i Jerry",
                "overview": "Jedno od najomiljenijih rivalstava u povijesti ponovno oživljava kad se Jerry useli u najljepši hotel New Yorka uoči \"vjenčanja stoljeća\", prisiljavajući očajnog organizatora vjenčanja da hitno zatraži nužne mjere. Zaposlenica Kayla ima zadatak riješiti problem glodavaca u hotelu prije važnog događaja. Kayla za pomoć uzima Toma kako bi zajednički zaustavili nestašnog Jerryja.\r Slijedi naravno epska bitka mačke i miša koja prijeti uništenjem njezine karijere, vjenčanja, a moguće i samog hotela. No uskoro se pojavljuje još veći problem: zlobni i ambiciozni djelatnik koji se urotio protiv njih troje.",
                "tagline": "",
                "language": "hr"
            },
            {
                "title": "Tom & Jerry",
                "overview": "",
                "tagline": "",
                "language": "id"
            },
            {
                "title": "Tom & Jerry",
                "overview": "Il topo Jerry si trasferisce nel miglior hotel di New York alla vigilia del \"matrimonio del secolo\", costringendo il disperato organizzatore dell'evento ad assumere il gatto Tom per sbarazzarsi di lui. La conseguente battaglia tra gatto e topo minaccia di distruggere la sua carriera, il matrimonio e forse l'hotel stesso. Ma presto, sorge un problema ancora più grande: uno staff diabolicamente ambizioso che cospira contro tutti e tre.",
                "tagline": "Miglior nemici peggiori amici",
                "language": "it"
            },
            {
                "title": "トムとジェリー",
                "overview": "ある日、新人のケイラ(クロエ・グレース・モレッツ)が働くニューヨークの高級ホテルに、ネズミのジェリーが引っ越してくる。そのホテルでは世紀のウエディングパーティーが開催されるが、ジェリーとその天敵の猫・トムのせいでパーティーはぶち壊しになる。2匹は自分たちの汚名を返上するために仕方なく手を組み、最高のウエディングパーティーを開こうとする。",
                "tagline": "大嫌いだけど、好き.",
                "language": "ja"
            },
            {
                "title": "톰과 제리",
                "overview": "생쥐 제리는 성대한 결혼식이 열리게 될 뉴욕의 한 고급 호텔로 이사를 오게 되고, 이벤트 플래너 카일라는 제리를 잡기 위해서 고양이 톰을 고용한다. 하지만 우당탕탕 사고뭉치들의 역대급 대소동은 카일라의 커리어는 물론 결혼식과 호텔까지도 위험에 빠뜨리게 되는데…",
                "tagline": "전 세계가 사랑한 라이벌 콤비 뉴욕을 발칵 뒤집는다!",
                "language": "ko"
            },
            {
                "title": "Tomas ir Džeris",
                "overview": "Klasikinės „Hanna-Barbera“ nuosavybės adaptacija, kuri atskleidžia, kaip susipažino Tomas ir Džeris ir kaip atsirado jų konkurencija.",
                "tagline": "",
                "language": "lt"
            },
            {
                "title": "Tom & Jerry",
                "overview": "Kayla maakt deel uit van het personeel van een 5-sterren hotel in New York. Er staat een huwelijk op de planning dat in het honderd dreigt te lopen. De ondeugende muis Jerry heeft zich namelijk in het hotel gevestigd. Kayla besluit hierdoor de straatkat Tom in het hotel te halen zodat hij Jerry kan doen verdwijnen.",
                "tagline": "Beste vijanden. De ergste vrienden.",
                "language": "nl"
            },
            {
                "title": "Tom & Jerry",
                "overview": "Tom the cat and Jerry the mouse get kicked out of their home and relocate to a fancy New York hotel, where a scrappy employee named Kayla will lose her job if she can’t evict Jerry before a high-class wedding at the hotel. Her solution? Hiring Tom to get rid of the pesky mouse.",
                "tagline": "Best of enemies. Worst of friends.",
                "language": "no"
            },
            {
                "title": "Tom & Jerry",
                "overview": "Jerry obiera sobie za mieszkanie najlepszy hotel w Nowym Jorku w przeddzień mającego się tam odbyć \"ślubu stulecia\". Tym samym zmusza zdesperowaną organizatorkę wesela do zatrudnienia Toma w celu pozbycia się gryzonia. Istna bitwa między kotem a myszą, do której dochodzi, może jednak zrujnować jej karierę, ceremonię, a być może nawet sam hotel. Wkrótce jednak pojawia się jeszcze większy problem: otóż przeciw całej trójce spiskuje diabolicznie ambitny pracownik.  opis dystrybutora kino",
                "tagline": "",
                "language": "pl"
            },
            {
                "title": "Tom & Jerry",
                "overview": "Tom, o gato, e Jerry, o rato, são expulsos de sua casa e mudam-se para um hotel chique em Nova York, onde uma funcionária problemática chamada Kayla irá perder o emprego se não despejar o Jerry antes do casamento. A sua solução? Contratar Tom para se ver livre do rato chato.",
                "tagline": "Piores amigos, melhores inimigos.",
                "language": "pt"
            },
            {
                "title": "Том и Джерри",
                "overview": "Кайла, работница престижного отеля, где обитает мышонок Джерри, рискующий нарушить ход дорогой свадьбы. Чтобы разобраться с грызуном, она нанимает уличного кота Тома, но решить проблему не так уж и просто.",
                "tagline": "Лучшие враги. Худшие друзья.",
                "language": "ru"
            },
            {
                "title": "Tom a Jerry",
                "overview": "Keď sa Jerry presťahuje do luxusného hotela na Manhattane, kde práve prebieha svadba storočia, jej zúfalá organizátorka si najme Toma, aby jej pomohol sa zbaviť myšiaka. Hon kocúra a myši vzápätí skoro zničí nielen jej kariéru a nadchádzajúca svadbu, ale aj skoro celý hotel.",
                "tagline": "",
                "language": "sk"
            },
            {
                "title": "Tom & Jerry",
                "overview": "",
                "tagline": "",
                "language": "sl"
            },
            {
                "title": "Том и Џери",
                "overview": "Мачак Том и миш Џери бивају избачени из свог дома и прелазе у раскошни њујоршки хотел, где ће погубљена радница по имену Кејла изгубити посао ако не успе да протера Џерија пре гламурозног венчања. Њено решење? Унајмити Тома да се отараси несносног миша.",
                "tagline": "Најбољи непријатељи. Најгори пријатељи.",
                "language": "sr"
            },
            {
                "title": "Tom & Jerry",
                "overview": "En av de mest älskvärda rivaliteterna genom tiderna får nytt liv när Jerry checkar in på New Yorks finaste hotell under bröllopsnatten av \"århundradets bröllop\". Detta tvingar en desperat eventplanerare att anställa Tom för att bli av med Jerry. Den följande katt och råtta-leken hotar att förstöra både bröllopet och hela hotellet. Men snart uppstår ett ännu större problem, en diaboliskt ambitiös person i personalen börjar kämpa mot Tom, Jerry och eventplaneraren.",
                "tagline": "Bästa fienderna. Värsta vännerna.",
                "language": "sv"
            },
            {
                "title": "ทอม แอนด์ เจอร์รี่",
                "overview": "ถึงเวลาของคู่หูคู่กัดออกมาไล่ฟัดกันอีกครั้งกับตัวอย่างแรกภาพยนตร์ “Tom and Jerry - ทอม แอนด์ เจอร์รี่” หนึ่งในคู่กัดที่เป็นที่รักที่สุดในประวัติศาสตร์จะกลับมาอีกครั้ง! เมื่อ เจอร์รี่ ย้ายไปอยู่ที่โรงแรมที่หรูหราที่สุดในมหานครนิวยอร์ก ณ ช่วงเวลาที่กำลังจะมีพิธีการแต่งงานสำคัญ เป็นเหตุให้ผู้จัดงานจำเป็นต้องจ้าง ทอม มาเพื่อกำจัดเขาให้ออกไปให้พ้นตา เกิดเป็นสงครามระหว่างแมวกับหนูที่อาจทำลายอาชีพการงานของผู้จัดงานคนนั้น ไปจนถึงพิธีแต่งงาน และชื่อเสียงอันโด่งดังของโรงแรม แถมสถานการณ์ยิ่งเลวร้ายไปกันใหญ่เมื่อมีพนักงานอีกหนึ่งคนที่พยายามเข้ามาเติมเชื้อเพลิงให้กับความวุ่นวายระหว่างพวกเขา",
                "tagline": "",
                "language": "th"
            },
            {
                "title": "Tom ve Jerry",
                "overview": "Genç bir kadın olan Kayla, yeni işi için oldukça heyecanlıdır. Posh Otel’de çalışmaya başlayan Kayla, kendisini kanıtlamak için her şeyi yapmaya hazırdır. Otel’de gerçekleştirilecek olan büyük bir düğün organizasyonunun hazırlığı sürmektedir ve sinir bozucu fare Jerry, düğünü mahvetmek için hazır bir şekilde beklemektedir. İşini garantilemek isteyen ve bu yüzden düğünü herhangi bir şeyin bozmasına engel olmak için çalışan Kalya, Jerry’yi etkilesiz hale getirmenin yolunu arar. Jerry’nin tüm geceyi mahvetmesini önlemek için de Tom adındaki bir sokak kedisinden yardım ister. Şeytani patronunun kendisini kapının önüne koymasını engellemek için Kayla, Tom birlikte hareket edip Jerry’yi durdurmanın yolunu bulmalıdır.",
                "tagline": "Düşmanların en iyisi. Arkadaşların en kötüsü.",
                "language": "tr"
            },
            {
                "title": "Том і Джеррі",
                "overview": "Коли Джеррі переїжджає в найдорожчий готель Нью-Йорка напередодні «весілля століття», весільна розпорядниця змушена найняти Тома, щоб здихатись від миші. Та війна між цими двома загрожує знищенням її кар'єри, весілля і, можливо, самого готелю. Але невдовзі постає ще більша проблема: диявольськи амбітний колега планує змову проти них трьох.",
                "tagline": "Найкращі вороги. Найгірші друзі.",
                "language": "uk"
            },
            {
                "title": "Tom và Jerry: Quậy Tung New York",
                "overview": "“Sau nhiều năm chành chọe, nay cặp kỳ phùng địch thủ nổi tiếng nhất thế giới Tom và Jerry đã làm hòa, khăn gói rời khỏi mái nhà chung, và bắt đầu hành trình của riêng mình. Chuột Jerry nay trú ngụ tại một khách sạn sang trọng, nơi chuẩn bị tổ chức một đám cưới Thế kỷ. Cô nhân viên mới Kayla được giao cho nhiệm vụ đuổi Jerry đi nên mang về một chàng mèo “mình đầy kinh nghiệm” đối phó với chuột, không ai khác chính là Tom. Và thế là cuộc chiến mèo - chuột lại nổ ra, kéo theo loạt rắc rối cho khách sạn, và biết bao tình huống dở khóc dở cười.“",
                "tagline": "",
                "language": "vi"
            },
            {
                "title": "猫和老鼠",
                "overview": "　　“超杀女”科洛·莫瑞兹饰演的少女凯拉刚刚入职豪华大酒店，就碰上了叫人头疼的难题——杰瑞竟然想在酒店里定居，令酒店最近承接的世纪婚礼岌岌可危。于是，汤姆被凯拉雇佣成为酒店员工，目的是赶走杰瑞，这对欢喜冤家就此展开了一场你追我赶的爆笑喜剧。",
                "tagline": "",
                "language": "zh"
            }
        ],
        "people": {
            "cast": [
                {
                    "character": "Kayla Forrester",
                    "characters": [
                        "Kayla Forrester"
                    ],
                    "person": {
                        "name": "Chloë Grace Moretz",
                        "ids": {
                            "trakt": 422169,
                            "slug": "chloe-grace-moretz",
                            "imdb": "nm1631269",
                            "tmdb": 56734,
                            "tvrage": 58446
                        }
                    }
                },
                {
                    "character": "Terence Mendoza",
                    "characters": [
                        "Terence Mendoza"
                    ],
                    "person": {
                        "name": "Michael Peña",
                        "ids": {
                            "trakt": 14069,
                            "slug": "michael-pena",
                            "imdb": "nm0671567",
                            "tmdb": 454,
                            "tvrage": 2730
                        }
                    }
                },
                {
                    "character": "Ben",
                    "characters": [
                        "Ben"
                    ],
                    "person": {
                        "name": "Colin Jost",
                        "ids": {
                            "trakt": 403649,
                            "slug": "colin-jost",
                            "imdb": "nm1906042",
                            "tmdb": 1226277,
                            "tvrage": null
                        }
                    }
                },
                {
                    "character": "Henry Dubros",
                    "characters": [
                        "Henry Dubros"
                    ],
                    "person": {
                        "name": "Rob Delaney",
                        "ids": {
                            "trakt": 252653,
                            "slug": "rob-delaney",
                            "imdb": "nm3008739",
                            "tmdb": 1091324,
                            "tvrage": null
                        }
                    }
                },
                {
                    "character": "Preeta",
                    "characters": [
                        "Preeta"
                    ],
                    "person": {
                        "name": "Pallavi Sharda",
                        "ids": {
                            "trakt": 239546,
                            "slug": "pallavi-sharda",
                            "imdb": "nm3354963",
                            "tmdb": 979599,
                            "tvrage": null
                        }
                    }
                },
                {
                    "character": "Cameron",
                    "characters": [
                        "Cameron"
                    ],
                    "person": {
                        "name": "Jordan Bolger",
                        "ids": {
                            "trakt": 699694,
                            "slug": "jordan-bolger",
                            "imdb": "nm6304865",
                            "tmdb": 1674734,
                            "tvrage": null
                        }
                    }
                },
                {
                    "character": "Joy the Bell Girl",
                    "characters": [
                        "Joy the Bell Girl"
                    ],
                    "person": {
                        "name": "Patsy Ferran",
                        "ids": {
                            "trakt": 601439,
                            "slug": "patsy-ferran",
                            "imdb": "nm7153076",
                            "tmdb": 1600085,
                            "tvrage": null
                        }
                    }
                },
                {
                    "character": "Chef Jackie",
                    "characters": [
                        "Chef Jackie"
                    ],
                    "person": {
                        "name": "Ken Jeong",
                        "ids": {
                            "trakt": 419888,
                            "slug": "ken-jeong",
                            "imdb": "nm0421822",
                            "tmdb": 83586,
                            "tvrage": 58323
                        }
                    }
                },
                {
                    "character": "Spike (voice)",
                    "characters": [
                        "Spike (voice)"
                    ],
                    "person": {
                        "name": "Bobby Cannavale",
                        "ids": {
                            "trakt": 412629,
                            "slug": "bobby-cannavale",
                            "imdb": "nm0134072",
                            "tmdb": 21127,
                            "tvrage": 32769
                        }
                    }
                },
                {
                    "character": "Butch (voice)",
                    "characters": [
                        "Butch (voice)"
                    ],
                    "person": {
                        "name": "Nicky Jam",
                        "ids": {
                            "trakt": 716729,
                            "slug": "nicky-jam",
                            "imdb": "nm7500905",
                            "tmdb": 1688196,
                            "tvrage": null
                        }
                    }
                },
                {
                    "character": "Lightning (voice)",
                    "characters": [
                        "Lightning (voice)"
                    ],
                    "person": {
                        "name": "Joey Wells",
                        "ids": {
                            "trakt": 290745,
                            "slug": "joey-wells",
                            "imdb": "nm1830312",
                            "tmdb": 1320508,
                            "tvrage": null
                        }
                    }
                },
                {
                    "character": "Meathead (voice)",
                    "characters": [
                        "Meathead (voice)"
                    ],
                    "person": {
                        "name": "Na'im Lynn",
                        "ids": {
                            "trakt": 185502,
                            "slug": "na-im-lynn",
                            "imdb": "nm3156655",
                            "tmdb": 576229,
                            "tvrage": null
                        }
                    }
                },
                {
                    "character": "Ash (voice)",
                    "characters": [
                        "Ash (voice)"
                    ],
                    "person": {
                        "name": "William Horton",
                        "ids": {
                            "trakt": 260643,
                            "slug": "william-horton",
                            "imdb": "nm3146142",
                            "tmdb": 1108643,
                            "tvrage": null
                        }
                    }
                },
                {
                    "character": "Topsy (voice)",
                    "characters": [
                        "Topsy (voice)"
                    ],
                    "person": {
                        "name": "Harry Ratchford",
                        "ids": {
                            "trakt": 290742,
                            "slug": "harry-ratchford",
                            "imdb": "nm5183398",
                            "tmdb": 1320506,
                            "tvrage": null
                        }
                    }
                },
                {
                    "character": "Angel, Devil Tom (voice)",
                    "characters": [
                        "Angel",
                        "Devil Tom (voice)"
                    ],
                    "person": {
                        "name": "Lil Rel Howery",
                        "ids": {
                            "trakt": 629607,
                            "slug": "lil-rel-howery",
                            "imdb": "nm2577076",
                            "tmdb": 1488961,
                            "tvrage": null
                        }
                    }
                },
                {
                    "character": "Real Estate Rat (voice)",
                    "characters": [
                        "Real Estate Rat (voice)"
                    ],
                    "person": {
                        "name": "Utkarsh Ambudkar",
                        "ids": {
                            "trakt": 201652,
                            "slug": "utkarsh-ambudkar",
                            "imdb": "nm2064295",
                            "tmdb": 929511,
                            "tvrage": null
                        }
                    }
                },
                {
                    "character": "Pigeon Announcer (voice)",
                    "characters": [
                        "Pigeon Announcer (voice)"
                    ],
                    "person": {
                        "name": "Tim Story",
                        "ids": {
                            "trakt": 416425,
                            "slug": "tim-story",
                            "imdb": "nm1103162",
                            "tmdb": 20400,
                            "tvrage": null
                        }
                    }
                },
                {
                    "character": "Mrs. Mehta",
                    "characters": [
                        "Mrs. Mehta"
                    ],
                    "person": {
                        "name": "Somi De Souza",
                        "ids": {
                            "trakt": 585422,
                            "slug": "somi-de-souza",
                            "imdb": "nm1934291",
                            "tmdb": 1561308,
                            "tvrage": null
                        }
                    }
                },
                {
                    "character": "Mr. Mehta",
                    "characters": [
                        "Mr. Mehta"
                    ],
                    "person": {
                        "name": "Ajay Chhabra",
                        "ids": {
                            "trakt": 1985011,
                            "slug": "ajay-chhabra",
                            "imdb": null,
                            "tmdb": 2799135,
                            "tvrage": null
                        }
                    }
                },
                {
                    "character": "Mr. Jacobson Snr.",
                    "characters": [
                        "Mr. Jacobson Snr."
                    ],
                    "person": {
                        "name": "Patrick Poletti",
                        "ids": {
                            "trakt": 20282,
                            "slug": "patrick-poletti",
                            "imdb": "nm0688995",
                            "tmdb": 24247,
                            "tvrage": null
                        }
                    }
                },
                {
                    "character": "Mrs. Jacobson",
                    "characters": [
                        "Mrs. Jacobson"
                    ],
                    "person": {
                        "name": "Janis Ahern",
                        "ids": {
                            "trakt": 480248,
                            "slug": "janis-ahern",
                            "imdb": "nm4273260",
                            "tmdb": 1405269,
                            "tvrage": null
                        }
                    }
                },
                {
                    "character": "Linda Perrybottom",
                    "characters": [
                        "Linda Perrybottom"
                    ],
                    "person": {
                        "name": "Camilla Arfwedson",
                        "ids": {
                            "trakt": 247267,
                            "slug": "camilla-arfwedson",
                            "imdb": "nm2268310",
                            "tmdb": 1073327,
                            "tvrage": null
                        }
                    }
                },
                {
                    "character": "Animal Control Officer",
                    "characters": [
                        "Animal Control Officer"
                    ],
                    "person": {
                        "name": "Joe Bone",
                        "ids": {
                            "trakt": 1320538,
                            "slug": "joe-bone",
                            "imdb": null,
                            "tmdb": 2159326,
                            "tvrage": null
                        }
                    }
                },
                {
                    "character": "Leo the Sous Chef",
                    "characters": [
                        "Leo the Sous Chef"
                    ],
                    "person": {
                        "name": "Edward Judge",
                        "ids": {
                            "trakt": 491866,
                            "slug": "edward-judge",
                            "imdb": null,
                            "tmdb": 1413424,
                            "tvrage": null
                        }
                    }
                },
                {
                    "character": "Annoyed Vendor",
                    "characters": [
                        "Annoyed Vendor"
                    ],
                    "person": {
                        "name": "Brian Bovell",
                        "ids": {
                            "trakt": 159636,
                            "slug": "brian-bovell",
                            "imdb": "nm0100598",
                            "tmdb": 1228665,
                            "tvrage": 3998
                        }
                    }
                },
                {
                    "character": "Passing Father",
                    "characters": [
                        "Passing Father"
                    ],
                    "person": {
                        "name": "David Nolan",
                        "ids": {
                            "trakt": 522794,
                            "slug": "david-nolan",
                            "imdb": "nm4267079",
                            "tmdb": 1441640,
                            "tvrage": null
                        }
                    }
                },
                {
                    "character": "Passing Child",
                    "characters": [
                        "Passing Child"
                    ],
                    "person": {
                        "name": "Jude Coward Nicoll",
                        "ids": {
                            "trakt": 2205630,
                            "slug": "jude-coward-nicoll",
                            "imdb": "nm10946969",
                            "tmdb": 3024068,
                            "tvrage": null
                        }
                    }
                },
                {
                    "character": "Lola",
                    "characters": [
                        "Lola"
                    ],
                    "person": {
                        "name": "Christina Chong",
                        "ids": {
                            "trakt": 196309,
                            "slug": "christina-chong",
                            "imdb": "nm2925304",
                            "tmdb": 472632,
                            "tvrage": null
                        }
                    }
                },
                {
                    "character": "Gavin The Doorman",
                    "characters": [
                        "Gavin The Doorman"
                    ],
                    "person": {
                        "name": "Daniel Adegboyega",
                        "ids": {
                            "trakt": 552743,
                            "slug": "daniel-adegboyega",
                            "imdb": "nm4089182",
                            "tmdb": 1474705,
                            "tvrage": null
                        }
                    }
                },
                {
                    "character": "Job Hopper Supervisor",
                    "characters": [
                        "Job Hopper Supervisor"
                    ],
                    "person": {
                        "name": "Craig Stein",
                        "ids": {
                            "trakt": 561087,
                            "slug": "craig-stein",
                            "imdb": "nm1270268",
                            "tmdb": 1489322,
                            "tvrage": null
                        }
                    }
                },
                {
                    "character": "Elephant Trainer",
                    "characters": [
                        "Elephant Trainer"
                    ],
                    "person": {
                        "name": "Edward Dogliani",
                        "ids": {
                            "trakt": 816901,
                            "slug": "edward-dogliani",
                            "imdb": "nm2589085",
                            "tmdb": 1768321,
                            "tvrage": null
                        }
                    }
                },
                {
                    "character": "Carriage Riding Kid",
                    "characters": [
                        "Carriage Riding Kid"
                    ],
                    "person": {
                        "name": "Josselyn Ospina Escobar",
                        "ids": {
                            "trakt": 2205455,
                            "slug": "josselyn-ospina-escobar",
                            "imdb": null,
                            "tmdb": 3024075,
                            "tvrage": null
                        }
                    }
                },
                {
                    "character": "Assistant Hotel Staff",
                    "characters": [
                        "Assistant Hotel Staff"
                    ],
                    "person": {
                        "name": "Ozuna",
                        "ids": {
                            "trakt": 1519157,
                            "slug": "ozuna",
                            "imdb": null,
                            "tmdb": 2228673,
                            "tvrage": null
                        }
                    }
                },
                {
                    "character": "Wedding Guest",
                    "characters": [
                        "Wedding Guest"
                    ],
                    "person": {
                        "name": "Paolo Bonolis",
                        "ids": {
                            "trakt": 164049,
                            "slug": "paolo-bonolis",
                            "imdb": "nm1244159",
                            "tmdb": 234746,
                            "tvrage": null
                        }
                    }
                },
                {
                    "character": "Person in Park",
                    "characters": [
                        "Person in Park"
                    ],
                    "person": {
                        "name": "Haley Bishop",
                        "ids": {
                            "trakt": 1020046,
                            "slug": "haley-bishop",
                            "imdb": "nm3749687",
                            "tmdb": 1929090,
                            "tvrage": null
                        }
                    }
                },
                {
                    "character": "Commuter",
                    "characters": [
                        "Commuter"
                    ],
                    "person": {
                        "name": "Norma Butikofer",
                        "ids": {
                            "trakt": 2205417,
                            "slug": "norma-butikofer",
                            "imdb": "nm5150492",
                            "tmdb": 3024079,
                            "tvrage": null
                        }
                    }
                },
                {
                    "character": "Commuter",
                    "characters": [
                        "Commuter"
                    ],
                    "person": {
                        "name": "Marc Wesley DeHaney",
                        "ids": {
                            "trakt": 1985013,
                            "slug": "marc-wesley-dehaney",
                            "imdb": null,
                            "tmdb": 2799140,
                            "tvrage": null
                        }
                    }
                },
                {
                    "character": "News Reporter",
                    "characters": [
                        "News Reporter"
                    ],
                    "person": {
                        "name": "Kerri McLean",
                        "ids": {
                            "trakt": 779281,
                            "slug": "kerri-mclean",
                            "imdb": null,
                            "tmdb": 1734990,
                            "tvrage": null
                        }
                    }
                },
                {
                    "character": "TV Announcer",
                    "characters": [
                        "TV Announcer"
                    ],
                    "person": {
                        "name": "Sophie Holland",
                        "ids": {
                            "trakt": 658051,
                            "slug": "sophie-holland-23dd7d61-5333-4962-ab5f-425064abfeda",
                            "imdb": "nm6807048",
                            "tmdb": 1640424,
                            "tvrage": null
                        }
                    }
                },
                {
                    "character": "Workman",
                    "characters": [
                        "Workman"
                    ],
                    "person": {
                        "name": "Joseph Begley",
                        "ids": {
                            "trakt": 2205473,
                            "slug": "joseph-begley",
                            "imdb": "nm10891576",
                            "tmdb": 3024086,
                            "tvrage": null
                        }
                    }
                },
                {
                    "character": "Limo Driver",
                    "characters": [
                        "Limo Driver"
                    ],
                    "person": {
                        "name": "Scott Coker",
                        "ids": {
                            "trakt": 2205516,
                            "slug": "scott-coker",
                            "imdb": "nm4243438",
                            "tmdb": 3024089,
                            "tvrage": null
                        }
                    }
                },
                {
                    "character": "Joe Buck",
                    "characters": [
                        "Joe Buck"
                    ],
                    "person": {
                        "name": "Joe Buck",
                        "ids": {
                            "trakt": 357085,
                            "slug": "joe-buck",
                            "imdb": "nm0118374",
                            "tmdb": 1233313,
                            "tvrage": 59408
                        }
                    }
                },
                {
                    "character": "Tom, Jerry (archive sounds) (uncredited)",
                    "characters": [
                        "Tom",
                        "Jerry (archive sounds) (uncredited)"
                    ],
                    "person": {
                        "name": "William Hanna",
                        "ids": {
                            "trakt": 414996,
                            "slug": "william-hanna",
                            "imdb": "nm0360253",
                            "tmdb": 13620,
                            "tvrage": 38797
                        }
                    }
                },
                {
                    "character": "Tom, Jerry (archive sounds) (uncredited)",
                    "characters": [
                        "Tom",
                        "Jerry (archive sounds) (uncredited)"
                    ],
                    "person": {
                        "name": "Mel Blanc",
                        "ids": {
                            "trakt": 294561,
                            "slug": "mel-blanc",
                            "imdb": "nm0000305",
                            "tmdb": 33923,
                            "tvrage": 26011
                        }
                    }
                },
                {
                    "character": "Tom, Jerry (archive sounds) (uncredited)",
                    "characters": [
                        "Tom",
                        "Jerry (archive sounds) (uncredited)"
                    ],
                    "person": {
                        "name": "June Foray",
                        "ids": {
                            "trakt": 299671,
                            "slug": "june-foray",
                            "imdb": "nm0004931",
                            "tmdb": 15098,
                            "tvrage": 13751
                        }
                    }
                },
                {
                    "character": "Tom, Jerry (voice) (uncredited)",
                    "characters": [
                        "Tom",
                        "Jerry (voice) (uncredited)"
                    ],
                    "person": {
                        "name": "Frank Welker",
                        "ids": {
                            "trakt": 9271,
                            "slug": "frank-welker",
                            "imdb": "nm0919798",
                            "tmdb": 15831,
                            "tvrage": 6
                        }
                    }
                },
                {
                    "character": "Tom (singing voice) (uncredited)",
                    "characters": [
                        "Tom (singing voice) (uncredited)"
                    ],
                    "person": {
                        "name": "T-Pain",
                        "ids": {
                            "trakt": 154593,
                            "slug": "t-pain",
                            "imdb": "nm2359047",
                            "tmdb": 224092,
                            "tvrage": null
                        }
                    }
                },
                {
                    "character": "Tom (uncredited)",
                    "characters": [
                        "Tom (uncredited)"
                    ],
                    "person": {
                        "name": "Brian Stepanek",
                        "ids": {
                            "trakt": 13895,
                            "slug": "brian-stepanek",
                            "imdb": "nm0826745",
                            "tmdb": 146391,
                            "tvrage": 27940
                        }
                    }
                },
                {
                    "character": "Press (uncredited)",
                    "characters": [
                        "Press (uncredited)"
                    ],
                    "person": {
                        "name": "Gianni Calchetti",
                        "ids": {
                            "trakt": 1539686,
                            "slug": "gianni-calchetti",
                            "imdb": "nm10541166",
                            "tmdb": 2355277,
                            "tvrage": null
                        }
                    }
                },
                {
                    "character": "Chef (uncredited)",
                    "characters": [
                        "Chef (uncredited)"
                    ],
                    "person": {
                        "name": "Joakim Skarli",
                        "ids": {
                            "trakt": 939103,
                            "slug": "joakim-skarli",
                            "imdb": "nm7813817",
                            "tmdb": 1853975,
                            "tvrage": null
                        }
                    }
                },
                {
                    "character": "Hotel Guest (uncredited)",
                    "characters": [
                        "Hotel Guest (uncredited)"
                    ],
                    "person": {
                        "name": "Wong Charlie",
                        "ids": {
                            "trakt": 1433123,
                            "slug": "wong-charlie",
                            "imdb": "nm10360936",
                            "tmdb": 2251721,
                            "tvrage": null
                        }
                    }
                },
                {
                    "character": "Yoga Instructor (uncredited)",
                    "characters": [
                        "Yoga Instructor (uncredited)"
                    ],
                    "person": {
                        "name": "Leandra Ryan",
                        "ids": {
                            "trakt": 1236759,
                            "slug": "leandra-ryan",
                            "imdb": "nm3278747",
                            "tmdb": 1513731,
                            "tvrage": null
                        }
                    }
                },
                {
                    "character": "Boyfriend (uncredited)",
                    "characters": [
                        "Boyfriend (uncredited)"
                    ],
                    "person": {
                        "name": "Jeremy Ang Jones",
                        "ids": {
                            "trakt": 1985012,
                            "slug": "jeremy-ang-jones",
                            "imdb": null,
                            "tmdb": 2799138,
                            "tvrage": null
                        }
                    }
                },
                {
                    "character": "Sadie (uncredited)",
                    "characters": [
                        "Sadie (uncredited)"
                    ],
                    "person": {
                        "name": "Eleanor Fanyinka",
                        "ids": {
                            "trakt": 1531331,
                            "slug": "eleanor-fanyinka",
                            "imdb": null,
                            "tmdb": 2347105,
                            "tvrage": null
                        }
                    }
                },
                {
                    "character": "Wealthy Man (uncredited)",
                    "characters": [
                        "Wealthy Man (uncredited)"
                    ],
                    "person": {
                        "name": "Mike Capozzola",
                        "ids": {
                            "trakt": 1583525,
                            "slug": "mike-capozzola",
                            "imdb": null,
                            "tmdb": 2399172,
                            "tvrage": null
                        }
                    }
                },
                {
                    "character": "Wealthy Woman (uncredited)",
                    "characters": [
                        "Wealthy Woman (uncredited)"
                    ],
                    "person": {
                        "name": "Camilla Rutherford",
                        "ids": {
                            "trakt": 419485,
                            "slug": "camilla-rutherford",
                            "imdb": "nm0751950",
                            "tmdb": 38809,
                            "tvrage": 176915
                        }
                    }
                },
                {
                    "character": "Bellhop (uncredited)",
                    "characters": [
                        "Bellhop (uncredited)"
                    ],
                    "person": {
                        "name": "Densil Jones",
                        "ids": {
                            "trakt": 1985015,
                            "slug": "densil-jones",
                            "imdb": null,
                            "tmdb": 2799142,
                            "tvrage": null
                        }
                    }
                },
                {
                    "character": "Chef (uncredited)",
                    "characters": [
                        "Chef (uncredited)"
                    ],
                    "person": {
                        "name": "Fuzuli Khabibillaev",
                        "ids": {
                            "trakt": 1985014,
                            "slug": "fuzuli-khabibillaev",
                            "imdb": null,
                            "tmdb": 2799141,
                            "tvrage": null
                        }
                    }
                }
            ],
            "crew": {
                "costume & make-up": [
                    {
                        "job": "Costume Designer",
                        "jobs": [
                            "Costume Designer"
                        ],
                        "person": {
                            "name": "Alison McCosh",
                            "ids": {
                                "trakt": 1096177,
                                "slug": "alison-mccosh",
                                "imdb": null,
                                "tmdb": 1999343,
                                "tvrage": null
                            }
                        }
                    }
                ],
                "production": [
                    {
                        "job": "Co-Producer",
                        "jobs": [
                            "Co-Producer"
                        ],
                        "person": {
                            "name": "Jon Silk",
                            "ids": {
                                "trakt": 200437,
                                "slug": "jon-silk",
                                "imdb": "nm1698314",
                                "tmdb": 928546,
                                "tvrage": null
                            }
                        }
                    },
                    {
                        "job": "Line Producer",
                        "jobs": [
                            "Line Producer"
                        ],
                        "person": {
                            "name": "Stacy Ekstein",
                            "ids": {
                                "trakt": 204776,
                                "slug": "stacy-ekstein",
                                "imdb": "nm1472639",
                                "tmdb": 1192224,
                                "tvrage": null
                            }
                        }
                    },
                    {
                        "job": "Casting",
                        "jobs": [
                            "Casting"
                        ],
                        "person": {
                            "name": "Lucinda Syson",
                            "ids": {
                                "trakt": 420,
                                "slug": "lucinda-syson",
                                "imdb": "nm0843514",
                                "tmdb": 1113,
                                "tvrage": null
                            }
                        }
                    },
                    {
                        "job": "Unit Production Manager, Executive Producer",
                        "jobs": [
                            "Unit Production Manager",
                            "Executive Producer"
                        ],
                        "person": {
                            "name": "Steve Harding",
                            "ids": {
                                "trakt": 725992,
                                "slug": "steve-harding",
                                "imdb": null,
                                "tmdb": 1697623,
                                "tvrage": null
                            }
                        }
                    },
                    {
                        "job": "Executive Producer",
                        "jobs": [
                            "Executive Producer"
                        ],
                        "person": {
                            "name": "Tim Story",
                            "ids": {
                                "trakt": 416425,
                                "slug": "tim-story",
                                "imdb": "nm1103162",
                                "tmdb": 20400,
                                "tvrage": null
                            }
                        }
                    },
                    {
                        "job": "Executive Producer",
                        "jobs": [
                            "Executive Producer"
                        ],
                        "person": {
                            "name": "Jesse Ehrman",
                            "ids": {
                                "trakt": 1820212,
                                "slug": "jesse-ehrman",
                                "imdb": null,
                                "tmdb": 2632928,
                                "tvrage": null
                            }
                        }
                    },
                    {
                        "job": "Executive Producer",
                        "jobs": [
                            "Executive Producer"
                        ],
                        "person": {
                            "name": "Adam Goodman",
                            "ids": {
                                "trakt": 21090,
                                "slug": "adam-goodman",
                                "imdb": "nm0328996",
                                "tmdb": 25457,
                                "tvrage": null
                            }
                        }
                    },
                    {
                        "job": "Executive Producer",
                        "jobs": [
                            "Executive Producer"
                        ],
                        "person": {
                            "name": "Sam Register",
                            "ids": {
                                "trakt": 141821,
                                "slug": "sam-register",
                                "imdb": "nm1882146",
                                "tmdb": 141043,
                                "tvrage": null
                            }
                        }
                    },
                    {
                        "job": "Executive Producer",
                        "jobs": [
                            "Executive Producer"
                        ],
                        "person": {
                            "name": "Allison Abbate",
                            "ids": {
                                "trakt": 26515,
                                "slug": "allison-abbate",
                                "imdb": "nm0007831",
                                "tmdb": 34894,
                                "tvrage": null
                            }
                        }
                    },
                    {
                        "job": "Producer",
                        "jobs": [
                            "Producer"
                        ],
                        "person": {
                            "name": "Christopher DeFaria",
                            "ids": {
                                "trakt": 51196,
                                "slug": "christopher-defaria",
                                "imdb": "nm0002211",
                                "tmdb": 66897,
                                "tvrage": 166699
                            }
                        }
                    }
                ],
                "visual effects": [
                    {
                        "job": "Animation Supervisor",
                        "jobs": [
                            "Animation Supervisor"
                        ],
                        "person": {
                            "name": "Mike Eames",
                            "ids": {
                                "trakt": 488047,
                                "slug": "mike-eames",
                                "imdb": "nm0247192",
                                "tmdb": 1410193,
                                "tvrage": null
                            }
                        }
                    },
                    {
                        "job": "Visual Effects Producer",
                        "jobs": [
                            "Visual Effects Producer"
                        ],
                        "person": {
                            "name": "Richard Yeomans",
                            "ids": {
                                "trakt": 1548518,
                                "slug": "richard-yeomans",
                                "imdb": null,
                                "tmdb": 2363531,
                                "tvrage": null
                            }
                        }
                    },
                    {
                        "job": "Visual Effects Supervisor",
                        "jobs": [
                            "Visual Effects Supervisor"
                        ],
                        "person": {
                            "name": "Frazer Churchill",
                            "ids": {
                                "trakt": 44402,
                                "slug": "frazer-churchill",
                                "imdb": "nm0161431",
                                "tmdb": 1335195,
                                "tvrage": null
                            }
                        }
                    }
                ],
                "crew": [
                    {
                        "job": "Stunt Coordinator",
                        "jobs": [
                            "Stunt Coordinator"
                        ],
                        "person": {
                            "name": "Paul Kennington",
                            "ids": {
                                "trakt": 229824,
                                "slug": "paul-kennington",
                                "imdb": "nm1300280",
                                "tmdb": 1278131,
                                "tvrage": null
                            }
                        }
                    }
                ],
                "directing": [
                    {
                        "job": "Second Assistant Director",
                        "jobs": [
                            "Second Assistant Director"
                        ],
                        "person": {
                            "name": "Gayle Dickie",
                            "ids": {
                                "trakt": 235134,
                                "slug": "gayle-dickie",
                                "imdb": "nm1333696",
                                "tmdb": 1055972,
                                "tvrage": null
                            }
                        }
                    },
                    {
                        "job": "First Assistant Director",
                        "jobs": [
                            "First Assistant Director"
                        ],
                        "person": {
                            "name": "William Dodds",
                            "ids": {
                                "trakt": 784961,
                                "slug": "william-dodds",
                                "imdb": null,
                                "tmdb": 1739826,
                                "tvrage": null
                            }
                        }
                    },
                    {
                        "job": "Director",
                        "jobs": [
                            "Director"
                        ],
                        "person": {
                            "name": "Tim Story",
                            "ids": {
                                "trakt": 416425,
                                "slug": "tim-story",
                                "imdb": "nm1103162",
                                "tmdb": 20400,
                                "tvrage": null
                            }
                        }
                    }
                ],
                "art": [
                    {
                        "job": "Art Direction",
                        "jobs": [
                            "Art Direction"
                        ],
                        "person": {
                            "name": "Peter Dorme",
                            "ids": {
                                "trakt": 456960,
                                "slug": "peter-dorme",
                                "imdb": "nm0233796",
                                "tmdb": 1388850,
                                "tvrage": null
                            }
                        }
                    },
                    {
                        "job": "Set Decoration",
                        "jobs": [
                            "Set Decoration"
                        ],
                        "person": {
                            "name": "Niamh Coulter",
                            "ids": {
                                "trakt": 169158,
                                "slug": "niamh-coulter",
                                "imdb": "nm0183536",
                                "tmdb": 965761,
                                "tvrage": null
                            }
                        }
                    },
                    {
                        "job": "Production Design",
                        "jobs": [
                            "Production Design"
                        ],
                        "person": {
                            "name": "James Hambidge",
                            "ids": {
                                "trakt": 49624,
                                "slug": "james-hambidge",
                                "imdb": "nm0357381",
                                "tmdb": 1034754,
                                "tvrage": null
                            }
                        }
                    }
                ],
                "sound": [
                    {
                        "job": "Original Music Composer",
                        "jobs": [
                            "Original Music Composer"
                        ],
                        "person": {
                            "name": "Christopher Lennertz",
                            "ids": {
                                "trakt": 421061,
                                "slug": "christopher-lennertz",
                                "imdb": "nm0501999",
                                "tmdb": 49911,
                                "tvrage": null
                            }
                        }
                    },
                    {
                        "job": "Music Supervisor",
                        "jobs": [
                            "Music Supervisor"
                        ],
                        "person": {
                            "name": "Kier Lehman",
                            "ids": {
                                "trakt": 586257,
                                "slug": "kier-lehman",
                                "imdb": "nm1550302",
                                "tmdb": 1530088,
                                "tvrage": null
                            }
                        }
                    }
                ],
                "writing": [
                    {
                        "job": "Characters",
                        "jobs": [
                            "Characters"
                        ],
                        "person": {
                            "name": "William Hanna",
                            "ids": {
                                "trakt": 414996,
                                "slug": "william-hanna",
                                "imdb": "nm0360253",
                                "tmdb": 13620,
                                "tvrage": 38797
                            }
                        }
                    },
                    {
                        "job": "Characters",
                        "jobs": [
                            "Characters"
                        ],
                        "person": {
                            "name": "Joseph Barbera",
                            "ids": {
                                "trakt": 414997,
                                "slug": "joseph-barbera",
                                "imdb": "nm0053484",
                                "tmdb": 13594,
                                "tvrage": 38798
                            }
                        }
                    },
                    {
                        "job": "Writer",
                        "jobs": [
                            "Writer"
                        ],
                        "person": {
                            "name": "Kevin Costello",
                            "ids": {
                                "trakt": 658497,
                                "slug": "kevin-costello",
                                "imdb": null,
                                "tmdb": 1640647,
                                "tvrage": null
                            }
                        }
                    }
                ],
                "camera": [
                    {
                        "job": "Director of Photography",
                        "jobs": [
                            "Director of Photography"
                        ],
                        "person": {
                            "name": "Alan Stewart",
                            "ids": {
                                "trakt": 509572,
                                "slug": "alan-stewart-6a681ba4-6f24-48fa-a907-136a67c10f47",
                                "imdb": "nm0829152",
                                "tmdb": 1429639,
                                "tvrage": null
                            }
                        }
                    }
                ],
                "editing": [
                    {
                        "job": "Editor",
                        "jobs": [
                            "Editor"
                        ],
                        "person": {
                            "name": "Peter S. Elliot",
                            "ids": {
                                "trakt": 43581,
                                "slug": "peter-s-elliot",
                                "imdb": "nm0007192",
                                "tmdb": 57769,
                                "tvrage": null
                            }
                        }
                    }
                ]
            }
        },
        "ratings": {
            "rating": 6.55806,
            "votes": 1197,
            "distribution": {
                "1": 44,
                "2": 26,
                "3": 41,
                "4": 66,
                "5": 129,
                "6": 269,
                "7": 234,
                "8": 156,
                "9": 66,
                "10": 157
            }
        },
        "relatedMovies": [
            {
                "title": "The Incredibles",
                "year": 2004,
                "ids": {
                    "trakt": 5065,
                    "slug": "the-incredibles-2004",
                    "imdb": "tt0317705",
                    "tmdb": 9806
                }
            },
            {
                "title": "Monsters University",
                "year": 2013,
                "ids": {
                    "trakt": 44679,
                    "slug": "monsters-university-2013",
                    "imdb": "tt1453405",
                    "tmdb": 62211
                }
            },
            {
                "title": "Cars 2",
                "year": 2011,
                "ids": {
                    "trakt": 34064,
                    "slug": "cars-2-2011",
                    "imdb": "tt1216475",
                    "tmdb": 49013
                }
            },
            {
                "title": "Toy Story 2",
                "year": 1999,
                "ids": {
                    "trakt": 706,
                    "slug": "toy-story-2-1999",
                    "imdb": "tt0120363",
                    "tmdb": 863
                }
            },
            {
                "title": "Toy Story 3",
                "year": 2010,
                "ids": {
                    "trakt": 5407,
                    "slug": "toy-story-3-2010",
                    "imdb": "tt0435761",
                    "tmdb": 10193
                }
            },
            {
                "title": "Finding Nemo",
                "year": 2003,
                "ids": {
                    "trakt": 8,
                    "slug": "finding-nemo-2003",
                    "imdb": "tt0266543",
                    "tmdb": 12
                }
            },
            {
                "title": "Cars 3",
                "year": 2017,
                "ids": {
                    "trakt": 159627,
                    "slug": "cars-3-2017",
                    "imdb": "tt3606752",
                    "tmdb": 260514
                }
            },
            {
                "title": "Onward",
                "year": 2020,
                "ids": {
                    "trakt": 355892,
                    "slug": "onward-2020",
                    "imdb": "tt7146812",
                    "tmdb": 508439
                }
            },
            {
                "title": "Cars",
                "year": 2006,
                "ids": {
                    "trakt": 762,
                    "slug": "cars-2006",
                    "imdb": "tt0317219",
                    "tmdb": 920
                }
            },
            {
                "title": "Finding Dory",
                "year": 2016,
                "ids": {
                    "trakt": 87254,
                    "slug": "finding-dory-2016",
                    "imdb": "tt2277860",
                    "tmdb": 127380
                }
            }
        ],
        "stats": {
            "watchers": 47518,
            "plays": 63358,
            "collectors": 12080,
            "comments": 24,
            "lists": 5897,
            "votes": 1198,
            "recommended": 23
        },
        "watching": 6
    },
    "name": "Tom & Jerry",
    "videoType": "movie"
}